sps.cpython-39-x86_64-linux-gnu.so
libsps-1.1.1.dist-info/LICENSE
libsps-1.1.1.dist-info/RECORD
libsps-1.1.1.dist-info/top_level.txt
libsps-1.1.1.dist-info/WHEEL
libsps-1.1.1.dist-info/METADATA
libsps.libs/libgcc_s-a04fdf82.so.1
libsps.libs/libstdc++-a9383cce.so.6.0.28
